thebeat/__init__.py
thebeat/_decorators.py
thebeat/_version.py
thebeat/_warnings.py
thebeat/helpers.py
thebeat/linguistic.py
thebeat/music.py
thebeat/stats.py
thebeat/utils.py
thebeat/visualization.py
thebeat/core/__init__.py
thebeat/core/sequence.py
thebeat/core/soundsequence.py
thebeat/core/soundstimulus.py
thebeat/resources/__init__.py
thebeat/resources/metronome_mono.wav
thebeat/resources/metronome_stereo.wav
thebeat-0.3.0.dist-info/licenses/LICENSE
thebeat-0.3.0.dist-info/METADATA
thebeat-0.3.0.dist-info/WHEEL
thebeat-0.3.0.dist-info/top_level.txt
thebeat-0.3.0.dist-info/RECORD
