Metadata-Version: 2.4
Name: thebeat
Version: 0.3.0
Summary: Python package for working with rhythms and other temporal sequences in science
Author-email: Jelle van der Werff <jellevanderwerff@gmail.com>, Yannick Jadoul <yannick.jadoul@gmail.com>
License: GNU General Public License v3 or later (GPLv3+)
Project-URL: Homepage, https://thebeat.readthedocs.io/
Project-URL: Documentation, https://thebeat.readthedocs.io/
Project-URL: Changelog, https://github.com/Jellevanderwerff/thebeat/releases
Project-URL: Bug Tracker, https://github.com/Jellevanderwerff/thebeat/issues
Project-URL: Source Code, https://github.com/Jellevanderwerff/thebeat
Keywords: music,rhythm,timing,cognitive science
Classifier: Development Status :: 4 - Beta
Classifier: Programming Language :: Python :: 3
Requires-Python: >=3.10
License-File: LICENSE
Requires-Dist: numpy
Requires-Dist: scipy
Requires-Dist: matplotlib
Requires-Dist: sounddevice
Requires-Dist: pandas
Requires-Dist: levenshtein
Provides-Extra: music-notation
Requires-Dist: abjad; extra == "music-notation"
Requires-Dist: lilypond; (sys_platform != "darwin" or platform_machine != "arm64") and extra == "music-notation"
Dynamic: license-file
